AUTHORS
LICENSE
MANIFEST.in
README.rst
setup.cfg
setup.py
modernpy/__init__.py
modernpy/modernpylib.py
modernpy/test.py
modernpy.egg-info/PKG-INFO
modernpy.egg-info/SOURCES.txt
modernpy.egg-info/dependency_links.txt
modernpy.egg-info/not-zip-safe
modernpy.egg-info/requires.txt
modernpy.egg-info/top_level.txt