Metadata-Version: 1.1
Name: modernpy
Version: 0.1.0
Summary: Extension methods for built-in type in Python.
Home-page: https://github.com/shinznatkid/modernpy
Author: Shinz Natkid
Author-email: shinznatkid@gmail.com
License: UNKNOWN
Platform: UNKNOWN
Classifier: Development Status :: 3 - Alpha
Classifier: Environment :: Console
Classifier: Environment :: Web Environment
Classifier: Intended Audience :: Developers
Classifier: Intended Audience :: System Administrators
Classifier: License :: OSI Approved :: MIT License
Classifier: Operating System :: MacOS :: MacOS X
Classifier: Operating System :: Microsoft
Classifier: Operating System :: POSIX
Classifier: Programming Language :: Python
